minio_extensions/__init__.py
minio_extensions/_typing.py
minio_extensions/environment.py
minio_extensions/exceptions.py
minio_extensions/extensions.py
minio_extensions/providers.py
minio_extensions/metadata/__init__.py
minio_extensions/metadata/constants.py
minio_extensions/metadata/metadata.py
minio_extensions-0.1.2.dist-info/LICENSE
minio_extensions-0.1.2.dist-info/METADATA
minio_extensions-0.1.2.dist-info/WHEEL
minio_extensions-0.1.2.dist-info/top_level.txt
minio_extensions-0.1.2.dist-info/RECORD
