Metadata-Version: 2.1
Name: minio-extensions
Version: 0.1.2
Summary: MinIO Python Extension Package for S3 Storage Operations
Home-page: https://github.com/chrisbewz/minio-extensions
Download-URL: https://github.com/chrisbewz/minio-extensions/releases
Author: Christian Celso Bewzenko
Author-email: crisbewz@gmail.com
License: Apache-2.0
Keywords: minio,minio-extensions
Classifier: Development Status :: 5 - Production/Stable
Classifier: Intended Audience :: Developers
Classifier: License :: OSI Approved :: Apache Software License
Classifier: Natural Language :: English
Classifier: Operating System :: OS Independent
Classifier: Programming Language :: Python
Classifier: Programming Language :: Python :: 3.8
Classifier: Programming Language :: Python :: 3.9
Classifier: Programming Language :: Python :: 3.10
Classifier: Programming Language :: Python :: 3.11
Classifier: Topic :: Software Development :: Libraries :: Python Modules
License-File: LICENSE
Requires-Dist: minio
Requires-Dist: urllib3
Requires-Dist: pydantic
Requires-Dist: typing
Requires-Dist: typing-extensions
Requires-Dist: python-dotenv
Requires-Dist: annotated-types
